redisdict/__init__.py
redisdict/exceptions.py
redisdict/redisdict.py
redisdict/utils.py
redisdict/tests/__init__.py
redisdict/tests/test_redis_dict.py
redisdict-0.0.3.dist-info/DESCRIPTION.rst
redisdict-0.0.3.dist-info/METADATA
redisdict-0.0.3.dist-info/metadata.json
redisdict-0.0.3.dist-info/RECORD
redisdict-0.0.3.dist-info/top_level.txt
redisdict-0.0.3.dist-info/WHEEL
